Workbook

Sheet Summary
A1: Routing benchmark: which model routes best (32 prompts, 2026-10-29)
A2: Model | B2: Prompts | C2: Parsed | D2: Tier accuracy | E2: Score in range | F2: Kind accuracy | G2: Risky misroutes | H2: Avg seconds | I2: Total cost ($) | J2: Cost per 1,000 prompts ($) | K2: Rank (tier accuracy)
A3: claude-haiku-4-5 | B3: =COUNTIFS(Results!$A$2:$A$321,$A3) -> 32 | C3: =COUNTIFS(Results!$A$2:$A$321,$A3,Results!$D$2:$D$321,"<>") -> 32 | D3: =IFERROR(SUMIFS(Results!$I$2:$I$321,Results!$A$2:$A$321,$A3)/B3,0) -> 0.96875 | E3: =IFERROR(SUMIFS(Results!$J$2:$J$321,Results!$A$2:$A$321,$A3)/B3,0) -> 0.96875 | F3: =IFERROR(SUMIFS(Results!$K$2:$K$321,Results!$A$2:$A$321,$A3)/B3,0) -> 0.71875 | G3: =SUMIFS(Results!$L$2:$L$321,Results!$A$2:$A$321,$A3) -> 0 | H3: =IFERROR(AVERAGEIFS(Results!$M$2:$M$321,Results!$A$2:$A$321,$A3),0) -> 18.104375 | I3: =SUMIFS(Results!$P$2:$P$321,Results!$A$2:$A$321,$A3) -> 0.12613 | J3: =IFERROR(I3/B3*1000,0) -> 3.9415625 | K3: =RANK(D3,$D$3:$D$12) -> 2
A4: claude-haiku-5-5 | B4: =COUNTIFS(Results!$A$2:$A$321,$A4) -> 32 | C4: =COUNTIFS(Results!$A$2:$A$321,$A4,Results!$D$2:$D$321,"<>") -> 32 | D4: =IFERROR(SUMIFS(Results!$I$2:$I$321,Results!$A$2:$A$321,$A4)/B4,0) -> 0.90625 | E4: =IFERROR(SUMIFS(Results!$J$2:$J$321,Results!$A$2:$A$321,$A4)/B4,0) -> 0.875 | F4: =IFERROR(SUMIFS(Results!$K$2:$K$321,Results!$A$2:$A$321,$A4)/B4,0) -> 0.84375 | G4: =SUMIFS(Results!$L$2:$L$321,Results!$A$2:$A$321,$A4) -> 0 | H4: =IFERROR(AVERAGEIFS(Results!$M$2:$M$321,Results!$A$2:$A$321,$A4),0) -> 14.084687 | I4: =SUMIFS(Results!$P$2:$P$321,Results!$A$2:$A$321,$A4) -> 0.006682 | J4: =IFERROR(I4/B4*1000,0) -> 0.2088125 | K4: =RANK(D4,$D$3:$D$12) -> 6
A5: claude-sonnet-5-5 | B5: =COUNTIFS(Results!$A$2:$A$321,$A5) -> 32 | C5: =COUNTIFS(Results!$A$2:$A$321,$A5,Results!$D$2:$D$321,"<>") -> 32 | D5: =IFERROR(SUMIFS(Results!$I$2:$I$321,Results!$A$2:$A$321,$A5)/B5,0) -> 0.96875 | E5: =IFERROR(SUMIFS(Results!$J$2:$J$321,Results!$A$2:$A$321,$A5)/B5,0) -> 0.9375 | F5: =IFERROR(SUMIFS(Results!$K$2:$K$321,Results!$A$2:$A$321,$A5)/B5,0) -> 0.90625 | G5: =SUMIFS(Results!$L$2:$L$321,Results!$A$2:$A$321,$A5) -> 0 | H5: =IFERROR(AVERAGEIFS(Results!$M$2:$M$321,Results!$A$2:$A$321,$A5),0) -> 13.081875 | I5: =SUMIFS(Results!$P$2:$P$321,Results!$A$2:$A$321,$A5) -> 0.02158 | J5: =IFERROR(I5/B5*1000,0) -> 0.674375 | K5: =RANK(D5,$D$3:$D$12) -> 2
A6: deepseek-pro | B6: =COUNTIFS(Results!$A$2:$A$321,$A6) -> 32 | C6: =COUNTIFS(Results!$A$2:$A$321,$A6,Results!$D$2:$D$321,"<>") -> 32 | D6: =IFERROR(SUMIFS(Results!$I$2:$I$321,Results!$A$2:$A$321,$A6)/B6,0) -> 0.8125 | E6: =IFERROR(SUMIFS(Results!$J$2:$J$321,Results!$A$2:$A$321,$A6)/B6,0) -> 0.75 | F6: =IFERROR(SUMIFS(Results!$K$2:$K$321,Results!$A$2:$A$321,$A6)/B6,0) -> 0.75 | G6: =SUMIFS(Results!$L$2:$L$321,Results!$A$2:$A$321,$A6) -> 1 | H6: =IFERROR(AVERAGEIFS(Results!$M$2:$M$321,Results!$A$2:$A$321,$A6),0) -> 5.3871875 | I6: =SUMIFS(Results!$P$2:$P$321,Results!$A$2:$A$321,$A6) -> 0.006827 | J6: =IFERROR(I6/B6*1000,0) -> 0.21334375 | K6: =RANK(D6,$D$3:$D$12) -> 10
A7: gemini-3.8-flash | B7: =COUNTIFS(Results!$A$2:$A$321,$A7) -> 32 | C7: =COUNTIFS(Results!$A$2:$A$321,$A7,Results!$D$2:$D$321,"<>") -> 32 | D7: =IFERROR(SUMIFS(Results!$I$2:$I$321,Results!$A$2:$A$321,$A7)/B7,0) -> 0.9375 | E7: =IFERROR(SUMIFS(Results!$J$2:$J$321,Results!$A$2:$A$321,$A7)/B7,0) -> 0.90625 | F7: =IFERROR(SUMIFS(Results!$K$2:$K$321,Results!$A$2:$A$321,$A7)/B7,0) -> 0.84375 | G7: =SUMIFS(Results!$L$2:$L$321,Results!$A$2:$A$321,$A7) -> 0 | H7: =IFERROR(AVERAGEIFS(Results!$M$2:$M$321,Results!$A$2:$A$321,$A7),0) -> 4.924375 | I7: =SUMIFS(Results!$P$2:$P$321,Results!$A$2:$A$321,$A7) -> 0.014472 | J7: =IFERROR(I7/B7*1000,0) -> 0.45225 | K7: =RANK(D7,$D$3:$D$12) -> 5
A8: glm-5.3 | B8: =COUNTIFS(Results!$A$2:$A$321,$A8) -> 32 | C8: =COUNTIFS(Results!$A$2:$A$321,$A8,Results!$D$2:$D$321,"<>") -> 32 | D8: =IFERROR(SUMIFS(Results!$I$2:$I$321,Results!$A$2:$A$321,$A8)/B8,0) -> 0.875 | E8: =IFERROR(SUMIFS(Results!$J$2:$J$321,Results!$A$2:$A$321,$A8)/B8,0) -> 0.875 | F8: =IFERROR(SUMIFS(Results!$K$2:$K$321,Results!$A$2:$A$321,$A8)/B8,0) -> 0.75 | G8: =SUMIFS(Results!$L$2:$L$321,Results!$A$2:$A$321,$A8) -> 0 | H8: =IFERROR(AVERAGEIFS(Results!$M$2:$M$321,Results!$A$2:$A$321,$A8),0) -> 6.5865625 | I8: =SUMIFS(Results!$P$2:$P$321,Results!$A$2:$A$321,$A8) -> 0.018544 | J8: =IFERROR(I8/B8*1000,0) -> 0.5795 | K8: =RANK(D8,$D$3:$D$12) -> 7
A9: gpt-6-luna | B9: =COUNTIFS(Results!$A$2:$A$321,$A9) -> 32 | C9: =COUNTIFS(Results!$A$2:$A$321,$A9,Results!$D$2:$D$321,"<>") -> 32 | D9: =IFERROR(SUMIFS(Results!$I$2:$I$321,Results!$A$2:$A$321,$A9)/B9,0) -> 1 | E9: =IFERROR(SUMIFS(Results!$J$2:$J$321,Results!$A$2:$A$321,$A9)/B9,0) -> 0.9375 | F9: =IFERROR(SUMIFS(Results!$K$2:$K$321,Results!$A$2:$A$321,$A9)/B9,0) -> 0.8125 | G9: =SUMIFS(Results!$L$2:$L$321,Results!$A$2:$A$321,$A9) -> 0 | H9: =IFERROR(AVERAGEIFS(Results!$M$2:$M$321,Results!$A$2:$A$321,$A9),0) -> 6.3221875 | I9: =SUMIFS(Results!$P$2:$P$321,Results!$A$2:$A$321,$A9) -> 0.002343 | J9: =IFERROR(I9/B9*1000,0) -> 0.07321875 | K9: =RANK(D9,$D$3:$D$12) -> 1
A10: gpt-6-sol | B10: =COUNTIFS(Results!$A$2:$A$321,$A10) -> 32 | C10: =COUNTIFS(Results!$A$2:$A$321,$A10,Results!$D$2:$D$321,"<>") -> 32 | D10: =IFERROR(SUMIFS(Results!$I$2:$I$321,Results!$A$2:$A$321,$A10)/B10,0) -> 0.96875 | E10: =IFERROR(SUMIFS(Results!$J$2:$J$321,Results!$A$2:$A$321,$A10)/B10,0) -> 0.9375 | F10: =IFERROR(SUMIFS(Results!$K$2:$K$321,Results!$A$2:$A$321,$A10)/B10,0) -> 0.875 | G10: =SUMIFS(Results!$L$2:$L$321,Results!$A$2:$A$321,$A10) -> 0 | H10: =IFERROR(AVERAGEIFS(Results!$M$2:$M$321,Results!$A$2:$A$321,$A10),0) -> 5.2515625 | I10: =SUMIFS(Results!$P$2:$P$321,Results!$A$2:$A$321,$A10) -> 0.042116 | J10: =IFERROR(I10/B10*1000,0) -> 1.316125 | K10: =RANK(D10,$D$3:$D$12) -> 2
A11: kimi-2.7-code | B11: =COUNTIFS(Results!$A$2:$A$321,$A11) -> 32 | C11: =COUNTIFS(Results!$A$2:$A$321,$A11,Results!$D$2:$D$321,"<>") -> 32 | D11: =IFERROR(SUMIFS(Results!$I$2:$I$321,Results!$A$2:$A$321,$A11)/B11,0) -> 0.875 | E11: =IFERROR(SUMIFS(Results!$J$2:$J$321,Results!$A$2:$A$321,$A11)/B11,0) -> 0.84375 | F11: =IFERROR(SUMIFS(Results!$K$2:$K$321,Results!$A$2:$A$321,$A11)/B11,0) -> 0.8125 | G11: =SUMIFS(Results!$L$2:$L$321,Results!$A$2:$A$321,$A11) -> 2 | H11: =IFERROR(AVERAGEIFS(Results!$M$2:$M$321,Results!$A$2:$A$321,$A11),0) -> 8.548125 | I11: =SUMIFS(Results!$P$2:$P$321,Results!$A$2:$A$321,$A11) -> 0.020567 | J11: =IFERROR(I11/B11*1000,0) -> 0.64271875 | K11: =RANK(D11,$D$3:$D$12) -> 7
A12: minimax-m3 | B12: =COUNTIFS(Results!$A$2:$A$321,$A12) -> 32 | C12: =COUNTIFS(Results!$A$2:$A$321,$A12,Results!$D$2:$D$321,"<>") -> 32 | D12: =IFERROR(SUMIFS(Results!$I$2:$I$321,Results!$A$2:$A$321,$A12)/B12,0) -> 0.84375 | E12: =IFERROR(SUMIFS(Results!$J$2:$J$321,Results!$A$2:$A$321,$A12)/B12,0) -> 0.78125 | F12: =IFERROR(SUMIFS(Results!$K$2:$K$321,Results!$A$2:$A$321,$A12)/B12,0) -> 0.6875 | G12: =SUMIFS(Results!$L$2:$L$321,Results!$A$2:$A$321,$A12) -> 2 | H12: =IFERROR(AVERAGEIFS(Results!$M$2:$M$321,Results!$A$2:$A$321,$A12),0) -> 5.0753125 | I12: =SUMIFS(Results!$P$2:$P$321,Results!$A$2:$A$321,$A12) -> 0.008079 | J12: =IFERROR(I12/B12*1000,0) -> 0.25246875 | K12: =RANK(D12,$D$3:$D$12) -> 9
A14: Tier accuracy: share of prompts routed to an acceptable tier (between the tiers of the expected min and max score).
A15: Risky misroutes: prompts that need Claude (critical) that the model would have sent to a cheaper model. The most important column: lower is safer.
A16: Cost per 1,000 prompts: what this model would cost as the router for 1,000 prompts, from this run. See Settings for how cost was measured.

Sheet Settings
A1: Routing benchmark: which model routes best
A2: Setting | B2: Value
A3: Simple tier: score at or below | B3: 3
A4: Coding tier: score at or below (above is critical) | B4: 7
A7: How to read this workbook
A8: Prompts: 32 labelled tasks, from creating a text file to a multi-tenant B2B SaaS. Min/Max is the score range a good router should give on the mod's blast-radius rubric; edit them (yellow) if you disagree.
A9: Results: one row per model and prompt: the model's raw reply, the verdict the mod would parse from it, and its time and cost.
A10: Summary: per model, how often it routed to an acceptable tier, how often it under-scored risky work (critical expected, routed below), and what routing 1,000 prompts would cost.
A11: Method: each model was asked the mod's exact classifier question (hooks/lib/classify.js classifierPrompt) once per prompt on 2026-10-29, and its reply parsed with the mod's parseVerdict rule.
A12: Palgu models: Anthropic API on api.palgu.ai, pinned with x-srooter-pin, max 400 output tokens; cost is Palgu's own /v1/pricing/quote for the usage returned.
A13: Claude models: claude -p on the user's login with a minimal system prompt; cost estimated at API list prices (Haiku 5.5 $0.10/$0.50, Haiku 4.5 $1/$5, Sonnet 5.5 $2/$10 per million) from the question size (~4 characters a token) and the reported output tokens, which include thinking.
A14: Not run: the local Ollama classifier (qwen2.5-coder:3b), because Ollama was not running.
A15: Legend: blue text with a yellow fill = an input you may change. Black = a formula.

Sheet Prompts
A1: ID | B1: Category | C1: Prompt | D1: Expected min score | E1: Expected max score | F1: Expected kind | G1: Lowest acceptable tier | H1: Highest acceptable tier
A2: 1 | B2: File | C2: Create a text file notes.txt containing the word hello | D2: 1 | E2: 2 | F2: code | G2: =IF(D2<=Settings!$B$3,"simple",IF(D2<=Settings!$B$4,"coding","critical")) -> simple | H2: =IF(E2<=Settings!$B$3,"simple",IF(E2<=Settings!$B$4,"coding","critical")) -> simple
A3: 2 | B3: Bash search | C3: Run a bash command to find every .py file in this repo that contains TODO | D3: 1 | E3: 2 | F3: code | G3: =IF(D3<=Settings!$B$3,"simple",IF(D3<=Settings!$B$4,"coding","critical")) -> simple | H3: =IF(E3<=Settings!$B$3,"simple",IF(E3<=Settings!$B$4,"coding","critical")) -> simple
A4: 3 | B4: Bash search | C4: grep the logs folder for ERROR and tell me how many times it appears | D4: 1 | E4: 2 | F4: data | G4: =IF(D4<=Settings!$B$3,"simple",IF(D4<=Settings!$B$4,"coding","critical")) -> simple | H4: =IF(E4<=Settings!$B$3,"simple",IF(E4<=Settings!$B$4,"coding","critical")) -> simple
A5: 4 | B5: Lookup | C5: How do I reverse a list in Python? | D5: 1 | E5: 2 | F5: research | G5: =IF(D5<=Settings!$B$3,"simple",IF(D5<=Settings!$B$4,"coding","critical")) -> simple | H5: =IF(E5<=Settings!$B$3,"simple",IF(E5<=Settings!$B$4,"coding","critical")) -> simple
A6: 5 | B6: Lookup | C6: Explain what this regex matches: ^\d{3}-\d{4}$ | D6: 1 | E6: 2 | F6: review | G6: =IF(D6<=Settings!$B$3,"simple",IF(D6<=Settings!$B$4,"coding","critical")) -> simple | H6: =IF(E6<=Settings!$B$3,"simple",IF(E6<=Settings!$B$4,"coding","critical")) -> simple
A7: 6 | B7: Git | C7: Show me git status and the last five commits | D7: 1 | E7: 2 | F7: code | G7: =IF(D7<=Settings!$B$3,"simple",IF(D7<=Settings!$B$4,"coding","critical")) -> simple | H7: =IF(E7<=Settings!$B$3,"simple",IF(E7<=Settings!$B$4,"coding","critical")) -> simple
A8: 7 | B8: Hello world | C8: Write a hello world program in Python and run it | D8: 1 | E8: 3 | F8: code | G8: =IF(D8<=Settings!$B$3,"simple",IF(D8<=Settings!$B$4,"coding","critical")) -> simple | H8: =IF(E8<=Settings!$B$3,"simple",IF(E8<=Settings!$B$4,"coding","critical")) -> simple
A9: 8 | B9: Hello world | C9: Create a hello world Express server that listens on port 3000 | D9: 2 | E9: 3 | F9: code | G9: =IF(D9<=Settings!$B$3,"simple",IF(D9<=Settings!$B$4,"coding","critical")) -> simple | H9: =IF(E9<=Settings!$B$3,"simple",IF(E9<=Settings!$B$4,"coding","critical")) -> simple
A10: 9 | B10: Small edit | C10: Rename the variable usr to user in src/utils.js | D10: 2 | E10: 3 | F10: code | G10: =IF(D10<=Settings!$B$3,"simple",IF(D10<=Settings!$B$4,"coding","critical")) -> simple | H10: =IF(E10<=Settings!$B$3,"simple",IF(E10<=Settings!$B$4,"coding","critical")) -> simple
A11: 10 | B11: Small edit | C11: Add a .gitignore for a Node project | D11: 2 | E11: 3 | F11: code | G11: =IF(D11<=Settings!$B$3,"simple",IF(D11<=Settings!$B$4,"coding","critical")) -> simple | H11: =IF(E11<=Settings!$B$3,"simple",IF(E11<=Settings!$B$4,"coding","critical")) -> simple
A12: 11 | B12: Docs | C12: Write a commit message for the staged changes | D12: 1 | E12: 3 | F12: docs | G12: =IF(D12<=Settings!$B$3,"simple",IF(D12<=Settings!$B$4,"coding","critical")) -> simple | H12: =IF(E12<=Settings!$B$3,"simple",IF(E12<=Settings!$B$4,"coding","critical")) -> simple
A13: 12 | B13: Docs | C13: Write a README for this project explaining setup and usage | D13: 2 | E13: 4 | F13: docs | G13: =IF(D13<=Settings!$B$3,"simple",IF(D13<=Settings!$B$4,"coding","critical")) -> simple | H13: =IF(E13<=Settings!$B$3,"simple",IF(E13<=Settings!$B$4,"coding","critical")) -> coding
... A33: 32 | B33: B2B SaaS | C33: Build a multi-tenant B2B SaaS: organisations, RBAC, SAML SSO, Stripe billing, audit logs, and Postgres row-level security between tenants | D33: 9 | E33: 10 | F33: code | G33: =IF(D33<=Settings!$B$3,"simple",IF(D33<=Settings!$B$4,"coding","critical")) -> critical | H33: =IF(E33<=Settings!$B$3,"simple",IF(E33<=Settings!$B$4,"coding","critical")) -> critical

Sheet Results
A1: Model | B1: Prompt ID | C1: Raw reply | D1: Score | E1: Kind | F1: Routed tier | G1: Expected min | H1: Expected max | I1: Tier OK | J1: Score in range | K1: Kind OK | L1: Risky misroute | M1: Seconds | N1: Tokens in | O1: Tokens out | P1: Cost ($) | Q1: Served model | R1: Error
A2: claude-haiku-4-5 | B2: 1 | C2: 1 docs | D2: 1 | E2: docs | F2: =IF(D2="","none",IF(D2<=Settings!$B$3,"simple",IF(D2<=Settings!$B$4,"coding","critical"))) -> simple | G2: =INDEX(Prompts!$D$2:$D$200,MATCH($B2,Prompts!$A$2:$A$200,0)) -> 1 | H2: =INDEX(Prompts!$E$2:$E$200,MATCH($B2,Prompts!$A$2:$A$200,0)) -> 2 | I2: =IF(D2="",0,IF(OR(F2=IF(G2<=Settings!$B$3,"simple",IF(G2<=Settings!$B$4,"coding","critical")),F2=IF(H2<=Settings!$B$3,"simple",IF(H2<=Settings!$B$4,"coding","critical"))),1,0)) -> 1 | J2: =IF(D2="",0,IF(AND(D2>=G2,D2<=H2),1,0)) -> 1 | K2: =IF(E2=INDEX(Prompts!$F$2:$F$200,MATCH($B2,Prompts!$A$2:$A$200,0)),1,0) -> 0 | L2: =IF(AND(G2>Settings!$B$4,OR(D2="",D2<=Settings!$B$4)),1,0) -> 0 | M2: 20.17 | N2: 307 | O2: 1179 | P2: 0.006202 | Q2: claude-haiku-4-5
A3: claude-haiku-4-5 | B3: 2 | C3: 1 research | D3: 1 | E3: research | F3: =IF(D3="","none",IF(D3<=Settings!$B$3,"simple",IF(D3<=Settings!$B$4,"coding","critical"))) -> simple | G3: =INDEX(Prompts!$D$2:$D$200,MATCH($B3,Prompts!$A$2:$A$200,0)) -> 1 | H3: =INDEX(Prompts!$E$2:$E$200,MATCH($B3,Prompts!$A$2:$A$200,0)) -> 2 | I3: =IF(D3="",0,IF(OR(F3=IF(G3<=Settings!$B$3,"simple",IF(G3<=Settings!$B$4,"coding","critical")),F3=IF(H3<=Settings!$B$3,"simple",IF(H3<=Settings!$B$4,"coding","critical"))),1,0)) -> 1 | J3: =IF(D3="",0,IF(AND(D3>=G3,D3<=H3),1,0)) -> 1 | K3: =IF(E3=INDEX(Prompts!$F$2:$F$200,MATCH($B3,Prompts!$A$2:$A$200,0)),1,0) -> 0 | L3: =IF(AND(G3>Settings!$B$4,OR(D3="",D3<=Settings!$B$4)),1,0) -> 0 | M3: 13.11 | N3: 312 | O3: 451 | P3: 0.002567 | Q3: claude-haiku-4-5
A4: claude-haiku-4-5 | B4: 3 | C4: 1 data | D4: 1 | E4: data | F4: =IF(D4="","none",IF(D4<=Settings!$B$3,"simple",IF(D4<=Settings!$B$4,"coding","critical"))) -> simple | G4: =INDEX(Prompts!$D$2:$D$200,MATCH($B4,Prompts!$A$2:$A$200,0)) -> 1 | H4: =INDEX(Prompts!$E$2:$E$200,MATCH($B4,Prompts!$A$2:$A$200,0)) -> 2 | I4: =IF(D4="",0,IF(OR(F4=IF(G4<=Settings!$B$3,"simple",IF(G4<=Settings!$B$4,"coding","critical")),F4=IF(H4<=Settings!$B$3,"simple",IF(H4<=Settings!$B$4,"coding","critical"))),1,0)) -> 1 | J4: =IF(D4="",0,IF(AND(D4>=G4,D4<=H4),1,0)) -> 1 | K4: =IF(E4=INDEX(Prompts!$F$2:$F$200,MATCH($B4,Prompts!$A$2:$A$200,0)),1,0) -> 1 | L4: =IF(AND(G4>Settings!$B$4,OR(D4="",D4<=Settings!$B$4)),1,0) -> 0 | M4: 11.73 | N4: 310 | O4: 335 | P4: 0.001985 | Q4: claude-haiku-4-5
A5: claude-haiku-4-5 | B5: 4 | C5: 1 research | D5: 1 | E5: research | F5: =IF(D5="","none",IF(D5<=Settings!$B$3,"simple",IF(D5<=Settings!$B$4,"coding","critical"))) -> simple | G5: =INDEX(Prompts!$D$2:$D$200,MATCH($B5,Prompts!$A$2:$A$200,0)) -> 1 | H5: =INDEX(Prompts!$E$2:$E$200,MATCH($B5,Prompts!$A$2:$A$200,0)) -> 2 | I5: =IF(D5="",0,IF(OR(F5=IF(G5<=Settings!$B$3,"simple",IF(G5<=Settings!$B$4,"coding","critical")),F5=IF(H5<=Settings!$B$3,"simple",IF(H5<=Settings!$B$4,"coding","critical"))),1,0)) -> 1 | J5: =IF(D5="",0,IF(AND(D5>=G5,D5<=H5),1,0)) -> 1 | K5: =IF(E5=INDEX(Prompts!$F$2:$F$200,MATCH($B5,Prompts!$A$2:$A$200,0)),1,0) -> 1 | L5: =IF(AND(G5>Settings!$B$4,OR(D5="",D5<=Settings!$B$4)),1,0) -> 0 | M5: 15.29 | N5: 302 | O5: 420 | P5: 0.002402 | Q5: claude-haiku-4-5
A6: claude-haiku-4-5 | B6: 5 | C6: 1 research | D6: 1 | E6: research | F6: =IF(D6="","none",IF(D6<=Settings!$B$3,"simple",IF(D6<=Settings!$B$4,"coding","critical"))) -> simple | G6: =INDEX(Prompts!$D$2:$D$200,MATCH($B6,Prompts!$A$2:$A$200,0)) -> 1 | H6: =INDEX(Prompts!$E$2:$E$200,MATCH($B6,Prompts!$A$2:$A$200,0)) -> 2 | I6: =IF(D6="",0,IF(OR(F6=IF(G6<=Settings!$B$3,"simple",IF(G6<=Settings!$B$4,"coding","critical")),F6=IF(H6<=Settings!$B$3,"simple",IF(H6<=Settings!$B$4,"coding","critical"))),1,0)) -> 1 | J6: =IF(D6="",0,IF(AND(D6>=G6,D6<=H6),1,0)) -> 1 | K6: =IF(E6=INDEX(Prompts!$F$2:$F$200,MATCH($B6,Prompts!$A$2:$A$200,0)),1,0) -> 0 | L6: =IF(AND(G6>Settings!$B$4,OR(D6="",D6<=Settings!$B$4)),1,0) -> 0 | M6: 24.69 | N6: 305 | O6: 1630 | P6: 0.008455 | Q6: claude-haiku-4-5
A7: claude-haiku-4-5 | B7: 6 | C7: 2 data | D7: 2 | E7: data | F7: =IF(D7="","none",IF(D7<=Settings!$B$3,"simple",IF(D7<=Settings!$B$4,"coding","critical"))) -> simple | G7: =INDEX(Prompts!$D$2:$D$200,MATCH($B7,Prompts!$A$2:$A$200,0)) -> 1 | H7: =INDEX(Prompts!$E$2:$E$200,MATCH($B7,Prompts!$A$2:$A$200,0)) -> 2 | I7: =IF(D7="",0,IF(OR(F7=IF(G7<=Settings!$B$3,"simple",IF(G7<=Settings!$B$4,"coding","critical")),F7=IF(H7<=Settings!$B$3,"simple",IF(H7<=Settings!$B$4,"coding","critical"))),1,0)) -> 1 | J7: =IF(D7="",0,IF(AND(D7>=G7,D7<=H7),1,0)) -> 1 | K7: =IF(E7=INDEX(Prompts!$F$2:$F$200,MATCH($B7,Prompts!$A$2:$A$200,0)),1,0) -> 0 | L7: =IF(AND(G7>Settings!$B$4,OR(D7="",D7<=Settings!$B$4)),1,0) -> 0 | M7: 23.02 | N7: 304 | O7: 1423 | P7: 0.007419 | Q7: claude-haiku-4-5
A8: claude-haiku-4-5 | B8: 7 | C8: 1 code | D8: 1 | E8: code | F8: =IF(D8="","none",IF(D8<=Settings!$B$3,"simple",IF(D8<=Settings!$B$4,"coding","critical"))) -> simple | G8: =INDEX(Prompts!$D$2:$D$200,MATCH($B8,Prompts!$A$2:$A$200,0)) -> 1 | H8: =INDEX(Prompts!$E$2:$E$200,MATCH($B8,Prompts!$A$2:$A$200,0)) -> 3 | I8: =IF(D8="",0,IF(OR(F8=IF(G8<=Settings!$B$3,"simple",IF(G8<=Settings!$B$4,"coding","critical")),F8=IF(H8<=Settings!$B$3,"simple",IF(H8<=Settings!$B$4,"coding","critical"))),1,0)) -> 1 | J8: =IF(D8="",0,IF(AND(D8>=G8,D8<=H8),1,0)) -> 1 | K8: =IF(E8=INDEX(Prompts!$F$2:$F$200,MATCH($B8,Prompts!$A$2:$A$200,0)),1,0) -> 1 | L8: =IF(AND(G8>Settings!$B$4,OR(D8="",D8<=Settings!$B$4)),1,0) -> 0 | M8: 13.16 | N8: 306 | O8: 420 | P8: 0.002406 | Q8: claude-haiku-4-5
A9: claude-haiku-4-5 | B9: 8 | C9: 3 code | D9: 3 | E9: code | F9: =IF(D9="","none",IF(D9<=Settings!$B$3,"simple",IF(D9<=Settings!$B$4,"coding","critical"))) -> simple | G9: =INDEX(Prompts!$D$2:$D$200,MATCH($B9,Prompts!$A$2:$A$200,0)) -> 2 | H9: =INDEX(Prompts!$E$2:$E$200,MATCH($B9,Prompts!$A$2:$A$200,0)) -> 3 | I9: =IF(D9="",0,IF(OR(F9=IF(G9<=Settings!$B$3,"simple",IF(G9<=Settings!$B$4,"coding","critical")),F9=IF(H9<=Settings!$B$3,"simple",IF(H9<=Settings!$B$4,"coding","critical"))),1,0)) -> 1 | J9: =IF(D9="",0,IF(AND(D9>=G9,D9<=H9),1,0)) -> 1 | K9: =IF(E9=INDEX(Prompts!$F$2:$F$200,MATCH($B9,Prompts!$A$2:$A$200,0)),1,0) -> 1 | L9: =IF(AND(G9>Settings!$B$4,OR(D9="",D9<=Settings!$B$4)),1,0) -> 0 | M9: 12.52 | N9: 309 | O9: 330 | P9: 0.001959 | Q9: claude-haiku-4-5
A10: claude-haiku-4-5 | B10: 9 | C10: 3 code | D10: 3 | E10: code | F10: =IF(D10="","none",IF(D10<=Settings!$B$3,"simple",IF(D10<=Settings!$B$4,"coding","critical"))) -> simple | G10: =INDEX(Prompts!$D$2:$D$200,MATCH($B10,Prompts!$A$2:$A$200,0)) -> 2 | H10: =INDEX(Prompts!$E$2:$E$200,MATCH($B10,Prompts!$A$2:$A$200,0)) -> 3 | I10: =IF(D10="",0,IF(OR(F10=IF(G10<=Settings!$B$3,"simple",IF(G10<=Settings!$B$4,"coding","critical")),F10=IF(H10<=Settings!$B$3,"simple",IF(H10<=Settings!$B$4,"coding","critical"))),1,0)) -> 1 | J10: =IF(D10="",0,IF(AND(D10>=G10,D10<=H10),1,0)) -> 1 | K10: =IF(E10=INDEX(Prompts!$F$2:$F$200,MATCH($B10,Prompts!$A$2:$A$200,0)),1,0) -> 1 | L10: =IF(AND(G10>Settings!$B$4,OR(D10="",D10<=Settings!$B$4)),1,0) -> 0 | M10: 12.93 | N10: 305 | O10: 514 | P10: 0.002875 | Q10: claude-haiku-4-5
A11: claude-haiku-4-5 | B11: 10 | C11: 3 code | D11: 3 | E11: code | F11: =IF(D11="","none",IF(D11<=Settings!$B$3,"simple",IF(D11<=Settings!$B$4,"coding","critical"))) -> simple | G11: =INDEX(Prompts!$D$2:$D$200,MATCH($B11,Prompts!$A$2:$A$200,0)) -> 2 | H11: =INDEX(Prompts!$E$2:$E$200,MATCH($B11,Prompts!$A$2:$A$200,0)) -> 3 | I11: =IF(D11="",0,IF(OR(F11=IF(G11<=Settings!$B$3,"simple",IF(G11<=Settings!$B$4,"coding","critical")),F11=IF(H11<=Settings!$B$3,"simple",IF(H11<=Settings!$B$4,"coding","critical"))),1,0)) -> 1 | J11: =IF(D11="",0,IF(AND(D11>=G11,D11<=H11),1,0)) -> 1 | K11: =IF(E11=INDEX(Prompts!$F$2:$F$200,MATCH($B11,Prompts!$A$2:$A$200,0)),1,0) -> 1 | L11: =IF(AND(G11>Settings!$B$4,OR(D11="",D11<=Settings!$B$4)),1,0) -> 0 | M11: 14.01 | N11: 302 | O11: 396 | P11: 0.002282 | Q11: claude-haiku-4-5
A12: claude-haiku-4-5 | B12: 11 | C12: 2 docs | D12: 2 | E12: docs | F12: =IF(D12="","none",IF(D12<=Settings!$B$3,"simple",IF(D12<=Settings!$B$4,"coding","critical"))) -> simple | G12: =INDEX(Prompts!$D$2:$D$200,MATCH($B12,Prompts!$A$2:$A$200,0)) -> 1 | H12: =INDEX(Prompts!$E$2:$E$200,MATCH($B12,Prompts!$A$2:$A$200,0)) -> 3 | I12: =IF(D12="",0,IF(OR(F12=IF(G12<=Settings!$B$3,"simple",IF(G12<=Settings!$B$4,"coding","critical")),F12=IF(H12<=Settings!$B$3,"simple",IF(H12<=Settings!$B$4,"coding","critical"))),1,0)) -> 1 | J12: =IF(D12="",0,IF(AND(D12>=G12,D12<=H12),1,0)) -> 1 | K12: =IF(E12=INDEX(Prompts!$F$2:$F$200,MATCH($B12,Prompts!$A$2:$A$200,0)),1,0) -> 1 | L12: =IF(AND(G12>Settings!$B$4,OR(D12="",D12<=Settings!$B$4)),1,0) -> 0 | M12: 14.28 | N12: 305 | O12: 448 | P12: 0.002545 | Q12: claude-haiku-4-5
A13: claude-haiku-4-5 | B13: 12 | C13: 3 docs | D13: 3 | E13: docs | F13: =IF(D13="","none",IF(D13<=Settings!$B$3,"simple",IF(D13<=Settings!$B$4,"coding","critical"))) -> simple | G13: =INDEX(Prompts!$D$2:$D$200,MATCH($B13,Prompts!$A$2:$A$200,0)) -> 2 | H13: =INDEX(Prompts!$E$2:$E$200,MATCH($B13,Prompts!$A$2:$A$200,0)) -> 4 | I13: =IF(D13="",0,IF(OR(F13=IF(G13<=Settings!$B$3,"simple",IF(G13<=Settings!$B$4,"coding","critical")),F13=IF(H13<=Settings!$B$3,"simple",IF(H13<=Settings!$B$4,"coding","critical"))),1,0)) -> 1 | J13: =IF(D13="",0,IF(AND(D13>=G13,D13<=H13),1,0)) -> 1 | K13: =IF(E13=INDEX(Prompts!$F$2:$F$200,MATCH($B13,Prompts!$A$2:$A$200,0)),1,0) -> 1 | L13: =IF(AND(G13>Settings!$B$4,OR(D13="",D13<=Settings!$B$4)),1,0) -> 0 | M13: 16.04 | N13: 308 | O13: 559 | P13: 0.003103 | Q13: claude-haiku-4-5
... A321: minimax-m3 | B321: 32 | C321: <think>We need answer two words blast radius and kind. Need evaluate task: build multi-tenant B2B SaaS orgs RBAC SAML SSO Stripe billing audit logs Postgres RLS multi tenants. Blast radius 9-10 security auth design architecture decisions, irreversible. It's code because build write code config. Need | D321: 9 | E321: code | F321: =IF(D321="","none",IF(D321<=Settings!$B$3,"simple",IF(D321<=Settings!$B$4,"coding","critical"))) -> critical | G321: =INDEX(Prompts!$D$2:$D$200,MATCH($B321,Prompts!$A$2:$A$200,0)) -> 9 | H321: =INDEX(Prompts!$E$2:$E$200,MATCH($B321,Prompts!$A$2:$A$200,0)) -> 10 | I321: =IF(D321="",0,IF(OR(F321=IF(G321<=Settings!$B$3,"simple",IF(G321<=Settings!$B$4,"coding","critical")),F321=IF(H321<=Settings!$B$3,"simple",IF(H321<=Settings!$B$4,"coding","critical"))),1,0)) -> 1 | J321: =IF(D321="",0,IF(AND(D321>=G321,D321<=H321),1,0)) -> 1 | K321: =IF(E321=INDEX(Prompts!$F$2:$F$200,MATCH($B321,Prompts!$A$2:$A$200,0)),1,0) -> 1 | L321: =IF(AND(G321>Settings!$B$4,OR(D321="",D321<=Settings!$B$4)),1,0) -> 0 | M321: 16.29 | N321: 360 | O321: 323 | P321: 0.000417 | Q321: MiniMax-M3
